pocketoptionapi_async/__init__.py
pocketoptionapi_async/client.py
pocketoptionapi_async/config.py
pocketoptionapi_async/connection_keep_alive.py
pocketoptionapi_async/connection_monitor.py
pocketoptionapi_async/constants.py
pocketoptionapi_async/exceptions.py
pocketoptionapi_async/models.py
pocketoptionapi_async/monitoring.py
pocketoptionapi_async/utils.py
pocketoptionapi_async/websocket_client.py
pocketoptionapi_async-2.0.1.dist-info/licenses/LICENSE
pocketoptionapi_async-2.0.1.dist-info/METADATA
pocketoptionapi_async-2.0.1.dist-info/WHEEL
pocketoptionapi_async-2.0.1.dist-info/top_level.txt
pocketoptionapi_async-2.0.1.dist-info/RECORD
