Metadata-Version: 2.4
Name: pocketoptionapi-async
Version: 2.0.1
Summary: A comprehensive, modern async Python API for PocketOption trading platform.
Author-email: PocketOptionAPI Team <contact@chipadevteam.com>
Maintainer-email: PocketOptionAPI Team <contact@chipadevteam.com>
License: MIT License
Project-URL: Homepage, https://github.com/ChipaDevTeam/PocketOptionAPI
Project-URL: Bug Tracker, https://github.com/ChipaDevTeam/PocketOptionAPI/issues
Classifier: Programming Language :: Python :: 3
Classifier: Programming Language :: Python :: 3.8
Classifier: Programming Language :: Python :: 3.9
Classifier: Programming Language :: Python :: 3.10
Classifier: Programming Language :: Python :: 3.11
Classifier: License :: OSI Approved :: MIT License
Classifier: Operating System :: OS Independent
Classifier: Development Status :: 5 - Production/Stable
Classifier: Intended Audience :: Developers
Classifier: Topic :: Software Development :: Libraries :: Python Modules
Requires-Python: >=3.8
License-File: LICENSE
Requires-Dist: aiohttp>=3.8.0
Requires-Dist: websockets>=11.0.0
Requires-Dist: asyncio
Requires-Dist: python-dotenv>=1.0.0
Requires-Dist: tzlocal>=4.0.0
Requires-Dist: typing-extensions>=4.0.0
Requires-Dist: rich>=13.0.0
Requires-Dist: selenium>=4.0.0
Requires-Dist: webdriver-manager>=4.0.0
Requires-Dist: psutil>=5.9.0
Requires-Dist: loguru>=0.7.2
Requires-Dist: pydantic>=2.0.0
Requires-Dist: pandas>=2.0.0
Dynamic: license-file
